giphy_magic.py
setup.py
giphy_ipython_magic.egg-info/PKG-INFO
giphy_ipython_magic.egg-info/SOURCES.txt
giphy_ipython_magic.egg-info/dependency_links.txt
giphy_ipython_magic.egg-info/requires.txt
giphy_ipython_magic.egg-info/top_level.txt