Metadata-Version: 1.1
Name: giphy-ipython-magic
Version: 0.0.2
Summary: giphy line magic for ipython 2 and 3
Home-page: https://github.com/AustinRochford/giphy-ipython-magic
Author: Austin Rochford
Author-email: austin.rochford@gmail.com
License: MIT
Keywords: ipython
Platform: any
Classifier: Development Status :: 4 - Beta
Classifier: Intended Audience :: Developers
Classifier: Operating System :: OS Independent
Classifier: Programming Language :: Python
